adb/__init__.py
adb/adb_commands.py
adb/adb_debug.py
adb/adb_protocol.py
adb/common.py
adb/common_cli.py
adb/fastboot.py
adb/fastboot_debug.py
adb/filesync_protocol.py
adb/sign_m2crypto.py
adb/sign_pycryptodome.py
adb/sign_pythonrsa.py
adb/usb_exceptions.py
adb_homeassistant-1.3.2.dist-info/LICENSE
adb_homeassistant-1.3.2.dist-info/METADATA
adb_homeassistant-1.3.2.dist-info/WHEEL
adb_homeassistant-1.3.2.dist-info/entry_points.txt
adb_homeassistant-1.3.2.dist-info/top_level.txt
adb_homeassistant-1.3.2.dist-info/RECORD
